AUTHORS.rst
CHANGELOG.rst
LICENSE
MANIFEST.in
README.rst
setup.py
downloads/__init__.py
downloads/admin.py
downloads/fields.py
downloads/managers.py
downloads/models.py
downloads/signals.py
downloads/tests.py
downloads/urls.py
downloads/views.py
downloads/fixtures/photosizes.json
downloads/management/__init__.py
downloads/management/__init__.pyc
downloads/management/commands/__init__.py
downloads/management/commands/adddownloads.py
downloads/migrations/0001_initial.py
downloads/migrations/0001_initial.pyc
downloads/migrations/0002_rename_imagemod_to_temporarydownload.py
downloads/migrations/0002_rename_imagemod_to_temporarydownload.pyc
downloads/migrations/0003_rename_imagemod_to_temporarydownload.py
downloads/migrations/0003_rename_imagemod_to_temporarydownload.pyc
downloads/migrations/0004_remove_do_not_list.py
downloads/migrations/0004_remove_do_not_list.pyc
downloads/migrations/__init__.py
downloads/migrations/__init__.pyc
downloads/templates/basic/downloads/download_list_category.html
downloads/templates/basic/downloads/inclusion_tags/download_category.html
downloads/templates/basic/downloads/inclusion_tags/download_list_item.html
downloads/templatetags/__init__.py
downloads/templatetags/__init__.pyc
downloads/templatetags/downloads_tags.py
downloads/templatetags/downloads_tags.pyc
jmbo_downloads.egg-info/PKG-INFO
jmbo_downloads.egg-info/SOURCES.txt
jmbo_downloads.egg-info/dependency_links.txt
jmbo_downloads.egg-info/not-zip-safe
jmbo_downloads.egg-info/requires.txt
jmbo_downloads.egg-info/top_level.txt